upgrade_dependencies/__init__.py
upgrade_dependencies/__main__.py
upgrade_dependencies/dependency.py
upgrade_dependencies/main.py
upgrade_dependencies/project.py
upgrade_dependencies/utils.py
upgrade_dependencies-0.2.1.dist-info/METADATA
upgrade_dependencies-0.2.1.dist-info/WHEEL
upgrade_dependencies-0.2.1.dist-info/entry_points.txt
upgrade_dependencies-0.2.1.dist-info/licenses/LICENSE
upgrade_dependencies-0.2.1.dist-info/RECORD
