Metadata-Version: 2.4
Name: upgrade-dependencies
Version: 0.2.1
Summary: Creates PRs for dependency updates in python projects
Author-email: Robbie van Leeuwen <robbie.vanleeuwen@gmail.com>
License: MIT License
License-File: LICENSE
Requires-Python: >=3.13
Requires-Dist: httpx~=0.27.2
Requires-Dist: packaging~=24.2
Requires-Dist: ruamel-yaml~=0.18.6
Requires-Dist: tomlkit~=0.13.2
Requires-Dist: typer~=0.13.1
